<?xml version="1.0" encoding="utf-8" ?>
<dwsync>
<file name="hola-fresca-mexican-food-sacramento.jpg" server="power.arc.losrios.edu/public_html/cisw321/" local="133148290740792594" remote="133151072420000000" Dst="1" />
<file name="hola-fresca-review-page.jpg" server="power.arc.losrios.edu/public_html/cisw321/" local="133149186407621314" remote="133151072420000000" Dst="1" />
<file name="hola-fresca-mexican-grill-bowls.jpg" server="power.arc.losrios.edu/public_html/cisw321/" local="133148315016195065" remote="133151072520000000" Dst="1" />
<file name="hola-fresca-mexican-grill-burritos.jpg" server="power.arc.losrios.edu/public_html/cisw321/" local="133148300278743002" remote="133151072520000000" Dst="1" />
<file name="hola-fresca-mexican-grill-quesadilla.jpg" server="power.arc.losrios.edu/public_html/cisw321/" local="133148327766425373" remote="133151072530000000" Dst="1" />
<file name="hola-fresca-mexican-grill-tacos.jpg" server="power.arc.losrios.edu/public_html/cisw321/" local="133148292908677734" remote="133151072530000000" Dst="1" />
<file name="hola-fresca-mexican-grill-tamale.jpg" server="power.arc.losrios.edu/public_html/cisw321/" local="133149218625089835" remote="133151072540000000" Dst="1" />
<file name="new-menu-hola-fresca.jpg" server="power.arc.losrios.edu/public_html/cisw321/" local="133147626949729899" remote="133151072540000000" Dst="1" />
<file name="restaurant-hola-fresca.jpg" server="power.arc.losrios.edu/public_html/cisw321/" local="133147624098745294" remote="133151072540000000" Dst="1" />
</dwsync>